anchore_syft-1.18.1.dist-info/RECORD
anchore_syft-1.18.1.dist-info/LICENSE
anchore_syft-1.18.1.dist-info/WHEEL
anchore_syft-1.18.1.dist-info/entry_points.txt
anchore_syft-1.18.1.dist-info/top_level.txt
anchore_syft-1.18.1.dist-info/METADATA
anchore_syft-1.18.1.data/data/CMakeLists.txt
anchore_syft-1.18.1.data/data/syft_version.cmake
anchore_syft-1.18.1.data/data/README.md
anchore_syft/_version.py
anchore_syft/__init__.py
anchore_syft/data/bin/syft
