Metadata-Version: 2.1
Name: anchore_syft
Version: 1.18.1
Summary: CLI tool for generating a Software Bill of Materials from container images and filesystems
License: Apache-2.0
Project-URL: homepage, https://github.com/anchore/syft
Project-URL: download_url, https://github.com/anchore/syft/releases
Project-URL: Source Code, https://github.com/nightlark/anchore-syft-wheel
Project-URL: Bug Tracker, https://github.com/nightlark/anchore-syft-wheel/issues
Keywords: anchore,syft,sbom
Classifier: License :: OSI Approved :: Apache Software License
Classifier: Operating System :: OS Independent
Classifier: Operating System :: MacOS :: MacOS X
Classifier: Operating System :: Microsoft :: Windows
Classifier: Operating System :: POSIX :: Linux
Classifier: Environment :: Console
Classifier: Development Status :: 5 - Production/Stable
Classifier: Intended Audience :: Developers
Classifier: Intended Audience :: Information Technology
Classifier: Intended Audience :: End Users/Desktop
Classifier: Topic :: Security
Classifier: Topic :: Utilities
License-File: LICENSE
